VMC/__init__.py
VMC/cleaning.py
VMC/colouring.py
VMC/compile.py
VMC/helpers.py
VMC/init_options.py
VMC/plot.py
VMC/precompute_A.py
VMC/protein.py
VMC/results.py
VisualiseMarkovCommunities-0.0.3.dist-info/LICENSE
VisualiseMarkovCommunities-0.0.3.dist-info/METADATA
VisualiseMarkovCommunities-0.0.3.dist-info/WHEEL
VisualiseMarkovCommunities-0.0.3.dist-info/top_level.txt
VisualiseMarkovCommunities-0.0.3.dist-info/RECORD
